{
    "stockpricequote": {
        "BSE": [
            {
                "t": "1738573741",
                "ap": "209.00",
                "cp": "209.00",
                "v": "50"
            },
            {
                "t": "1738574145",
                "ap": "209.00",
                "cp": "209.00",
                "v": "50"
            },
            {
                "t": "1738574207",
                "ap": "209.00",
                "cp": "209.00",
                "v": "50"
            },
            {
                "t": "1738574278",
                "ap": "209.00",
                "cp": "209.00",
                "v": "50"
            },
            {
                "t": "1738574325",
                "ap": "209.00",
                "cp": "209.00",
                "v": "50"
            },
            {
                "t": "1738574363",
                "ap": "209.00",
                "cp": "209.00",
                "v": "50"
            },
            {
                "t": "1738574438",
                "ap": "209.00",
                "cp": "209.00",
                "v": "50"
            },
            {
                "t": "1738574460",
                "ap": "209.00",
                "cp": "209.00",
                "v": "50"
            },
            {
                "t": "1738574564",
                "ap": "209.00",
                "cp": "209.00",
                "v": "50"
            },
            {
                "t": "1738574638",
                "ap": "208.37",
                "cp": "208.25",
                "v": "250"
            },
            {
                "t": "1738574670",
                "ap": "208.37",
                "cp": "208.25",
                "v": "250"
            },
            {
                "t": "1738574748",
                "ap": "208.37",
                "cp": "208.25",
                "v": "250"
            },
            {
                "t": "1738574794",
                "ap": "208.37",
                "cp": "208.25",
                "v": "250"
            },
            {
                "t": "1738574872",
                "ap": "208.37",
                "cp": "208.25",
                "v": "250"
            },
            {
                "t": "1738574939",
                "ap": "208.37",
                "cp": "208.25",
                "v": "250"
            },
            {
                "t": "1738574989",
                "ap": "208.37",
                "cp": "208.25",
                "v": "253"
            },
            {
                "t": "1738575062",
                "ap": "208.37",
                "cp": "208.25",
                "v": "253"
            },
            {
                "t": "1738575349",
                "ap": "208.37",
                "cp": "208.25",
                "v": "253"
            },
            {
                "t": "1738575416",
                "ap": "208.37",
                "cp": "208.25",
                "v": "253"
            },
            {
                "t": "1738575494",
                "ap": "208.37",
                "cp": "208.25",
                "v": "253"
            },
            {
                "t": "1738575596",
                "ap": "208.37",
                "cp": "208.25",
                "v": "253"
            },
            {
                "t": "1738575845",
                "ap": "208.37",
                "cp": "208.25",
                "v": "253"
            },
            {
                "t": "1738576067",
                "ap": "208.37",
                "cp": "208.25",
                "v": "253"
            },
            {
                "t": "1738576184",
                "ap": "208.26",
                "cp": "208.00",
                "v": "353"
            },
            {
                "t": "1738576218",
                "ap": "208.26",
                "cp": "208.00",
                "v": "353"
            },
            {
                "t": "1738576483",
                "ap": "208.26",
                "cp": "208.00",
                "v": "353"
            },
            {
                "t": "1738576761",
                "ap": "208.26",
                "cp": "208.00",
                "v": "353"
            },
            {
                "t": "1738577037",
                "ap": "208.26",
                "cp": "208.00",
                "v": "353"
            },
            {
                "t": "1738577111",
                "ap": "208.25",
                "cp": "207.80",
                "v": "359"
            },
            {
                "t": "1738577160",
                "ap": "208.25",
                "cp": "207.80",
                "v": "364"
            },
            {
                "t": "1738577275",
                "ap": "208.25",
                "cp": "207.80",
                "v": "364"
            },
            {
                "t": "1738577293",
                "ap": "208.25",
                "cp": "207.80",
                "v": "364"
            },
            {
                "t": "1738577441",
                "ap": "208.25",
                "cp": "207.80",
                "v": "364"
            },
            {
                "t": "1738577481",
                "ap": "208.25",
                "cp": "207.80",
                "v": "364"
            },
            {
                "t": "1738577558",
                "ap": "208.25",
                "cp": "207.80",
                "v": "364"
            },
            {
                "t": "1738577612",
                "ap": "208.25",
                "cp": "207.80",
                "v": "364"
            },
            {
                "t": "1738577865",
                "ap": "208.25",
                "cp": "207.80",
                "v": "364"
            },
            {
                "t": "1738577931",
                "ap": "206.32",
                "cp": "203.00",
                "v": "587"
            },
            {
                "t": "1738578043",
                "ap": "204.42",
                "cp": "203.00",
                "v": "1364"
            },
            {
                "t": "1738578101",
                "ap": "204.42",
                "cp": "203.00",
                "v": "1364"
            },
            {
                "t": "1738578168",
                "ap": "204.22",
                "cp": "203.00",
                "v": "1587"
            },
            {
                "t": "1738578229",
                "ap": "204.22",
                "cp": "203.00",
                "v": "1587"
            },
            {
                "t": "1738578503",
                "ap": "204.22",
                "cp": "203.00",
                "v": "1588"
            },
            {
                "t": "1738578697",
                "ap": "204.21",
                "cp": "203.00",
                "v": "1606"
            },
            {
                "t": "1738578931",
                "ap": "204.17",
                "cp": "203.00",
                "v": "1657"
            },
            {
                "t": "1738579008",
                "ap": "204.17",
                "cp": "203.00",
                "v": "1657"
            },
            {
                "t": "1738579066",
                "ap": "204.17",
                "cp": "203.00",
                "v": "1657"
            },
            {
                "t": "1738579195",
                "ap": "204.17",
                "cp": "203.00",
                "v": "1657"
            },
            {
                "t": "1738579200",
                "ap": "204.17",
                "cp": "203.00",
                "v": "1657"
            },
            {
                "t": "1738579341",
                "ap": "204.17",
                "cp": "203.00",
                "v": "1657"
            },
            {
                "t": "1738579447",
                "ap": "204.17",
                "cp": "203.00",
                "v": "1658"
            },
            {
                "t": "1738579550",
                "ap": "204.12",
                "cp": "203.00",
                "v": "1738"
            },
            {
                "t": "1738579603",
                "ap": "204.11",
                "cp": "203.00",
                "v": "1748"
            },
            {
                "t": "1738579716",
                "ap": "204.11",
                "cp": "203.00",
                "v": "1748"
            },
            {
                "t": "1738579743",
                "ap": "204.11",
                "cp": "203.00",
                "v": "1748"
            },
            {
                "t": "1738579978",
                "ap": "203.17",
                "cp": "201.00",
                "v": "2748"
            },
            {
                "t": "1738580024",
                "ap": "202.91",
                "cp": "201.00",
                "v": "3119"
            },
            {
                "t": "1738580079",
                "ap": "202.91",
                "cp": "201.00",
                "v": "3119"
            },
            {
                "t": "1738580125",
                "ap": "202.91",
                "cp": "201.00",
                "v": "3119"
            },
            {
                "t": "1738580218",
                "ap": "202.91",
                "cp": "201.00",
                "v": "3119"
            },
            {
                "t": "1738580274",
                "ap": "202.91",
                "cp": "201.00",
                "v": "3119"
            },
            {
                "t": "1738580391",
                "ap": "202.91",
                "cp": "201.00",
                "v": "3119"
            },
            {
                "t": "1738580560",
                "ap": "202.91",
                "cp": "201.00",
                "v": "3119"
            },
            {
                "t": "1738580737",
                "ap": "202.91",
                "cp": "201.00",
                "v": "3119"
            },
            {
                "t": "1738580762",
                "ap": "202.91",
                "cp": "201.00",
                "v": "3119"
            },
            {
                "t": "1738580879",
                "ap": "202.91",
                "cp": "201.00",
                "v": "3119"
            },
            {
                "t": "1738580929",
                "ap": "202.91",
                "cp": "201.00",
                "v": "3119"
            },
            {
                "t": "1738581522",
                "ap": "202.91",
                "cp": "203.00",
                "v": "3229"
            },
            {
                "t": "1738581673",
                "ap": "202.91",
                "cp": "203.00",
                "v": "3229"
            },
            {
                "t": "1738581787",
                "ap": "202.91",
                "cp": "203.00",
                "v": "3229"
            },
            {
                "t": "1738581951",
                "ap": "202.92",
                "cp": "203.00",
                "v": "3619"
            },
            {
                "t": "1738582007",
                "ap": "202.92",
                "cp": "203.00",
                "v": "3729"
            },
            {
                "t": "1738582067",
                "ap": "202.94",
                "cp": "203.00",
                "v": "4619"
            },
            {
                "t": "1738582376",
                "ap": "203.82",
                "cp": "207.00",
                "v": "7619"
            },
            {
                "t": "1738582439",
                "ap": "204.48",
                "cp": "207.00",
                "v": "9564"
            },
            {
                "t": "1738582499",
                "ap": "205.27",
                "cp": "207.00",
                "v": "13979"
            },
            {
                "t": "1738582553",
                "ap": "205.27",
                "cp": "207.00",
                "v": "13979"
            },
            {
                "t": "1738582618",
                "ap": "205.27",
                "cp": "204.10",
                "v": "13989"
            },
            {
                "t": "1738582671",
                "ap": "205.27",
                "cp": "204.10",
                "v": "13989"
            },
            {
                "t": "1738582711",
                "ap": "205.27",
                "cp": "204.10",
                "v": "13989"
            },
            {
                "t": "1738582834",
                "ap": "205.27",
                "cp": "204.10",
                "v": "13989"
            },
            {
                "t": "1738582882",
                "ap": "205.27",
                "cp": "206.00",
                "v": "14000"
            },
            {
                "t": "1738582962",
                "ap": "205.27",
                "cp": "206.00",
                "v": "14000"
            },
            {
                "t": "1738583090",
                "ap": "205.28",
                "cp": "207.00",
                "v": "14100"
            },
            {
                "t": "1738583116",
                "ap": "205.28",
                "cp": "207.00",
                "v": "14100"
            },
            {
                "t": "1738583205",
                "ap": "205.28",
                "cp": "207.00",
                "v": "14100"
            },
            {
                "t": "1738583459",
                "ap": "205.28",
                "cp": "207.00",
                "v": "14100"
            },
            {
                "t": "1738583491",
                "ap": "205.28",
                "cp": "207.00",
                "v": "14100"
            },
            {
                "t": "1738583576",
                "ap": "205.28",
                "cp": "207.00",
                "v": "14100"
            },
            {
                "t": "1738583773",
                "ap": "205.28",
                "cp": "207.00",
                "v": "14100"
            },
            {
                "t": "1738583900",
                "ap": "205.28",
                "cp": "207.00",
                "v": "14100"
            },
            {
                "t": "1738583998",
                "ap": "205.28",
                "cp": "207.00",
                "v": "14100"
            },
            {
                "t": "1738584025",
                "ap": "205.28",
                "cp": "207.00",
                "v": "14100"
            },
            {
                "t": "1738584163",
                "ap": "205.28",
                "cp": "207.00",
                "v": "14100"
            },
            {
                "t": "1738584237",
                "ap": "205.28",
                "cp": "207.00",
                "v": "14100"
            },
            {
                "t": "1738584285",
                "ap": "205.33",
                "cp": "206.00",
                "v": "14991"
            },
            {
                "t": "1738584338",
                "ap": "205.33",
                "cp": "206.00",
                "v": "14991"
            },
            {
                "t": "1738584510",
                "ap": "205.33",
                "cp": "206.00",
                "v": "14991"
            },
            {
                "t": "1738584589",
                "ap": "205.33",
                "cp": "206.00",
                "v": "14991"
            },
            {
                "t": "1738585654",
                "ap": "205.33",
                "cp": "206.00",
                "v": "14991"
            },
            {
                "t": "1738585841",
                "ap": "205.33",
                "cp": "206.00",
                "v": "14991"
            },
            {
                "t": "1738585912",
                "ap": "205.32",
                "cp": "205.25",
                "v": "15291"
            },
            {
                "t": "1738585928",
                "ap": "205.32",
                "cp": "205.25",
                "v": "15291"
            },
            {
                "t": "1738586061",
                "ap": "205.32",
                "cp": "204.45",
                "v": "15391"
            },
            {
                "t": "1738586153",
                "ap": "205.32",
                "cp": "204.45",
                "v": "15391"
            },
            {
                "t": "1738586166",
                "ap": "205.32",
                "cp": "204.45",
                "v": "15391"
            },
            {
                "t": "1738586309",
                "ap": "205.32",
                "cp": "204.45",
                "v": "15391"
            },
            {
                "t": "1738586399",
                "ap": "205.32",
                "cp": "204.45",
                "v": "15391"
            },
            {
                "t": "1738586414",
                "ap": "205.32",
                "cp": "204.45",
                "v": "15391"
            },
            {
                "t": "1738586578",
                "ap": "205.32",
                "cp": "204.45",
                "v": "15391"
            },
            {
                "t": "1738587931",
                "ap": "205.32",
                "cp": "204.45",
                "v": "15391"
            },
            {
                "t": "1738588075",
                "ap": "205.32",
                "cp": "204.45",
                "v": "15391"
            },
            {
                "t": "1738588080",
                "ap": "205.32",
                "cp": "204.45",
                "v": "15391"
            },
            {
                "t": "1738588236",
                "ap": "205.32",
                "cp": "204.45",
                "v": "15391"
            },
            {
                "t": "1738588546",
                "ap": "205.32",
                "cp": "204.45",
                "v": "15391"
            },
            {
                "t": "1738588618",
                "ap": "205.32",
                "cp": "204.45",
                "v": "15391"
            },
            {
                "t": "1738588634",
                "ap": "205.47",
                "cp": "206.00",
                "v": "19768"
            },
            {
                "t": "1738588827",
                "ap": "205.47",
                "cp": "207.00",
                "v": "19793"
            },
            {
                "t": "1738588970",
                "ap": "205.47",
                "cp": "207.00",
                "v": "19793"
            },
            {
                "t": "1738589140",
                "ap": "205.47",
                "cp": "207.00",
                "v": "19793"
            },
            {
                "t": "1738589386",
                "ap": "205.49",
                "cp": "207.50",
                "v": "19993"
            },
            {
                "t": "1738589453",
                "ap": "205.49",
                "cp": "207.50",
                "v": "19993"
            },
            {
                "t": "1738589462",
                "ap": "205.64",
                "cp": "207.50",
                "v": "21593"
            },
            {
                "t": "1738589530",
                "ap": "205.64",
                "cp": "207.50",
                "v": "21593"
            },
            {
                "t": "1738589747",
                "ap": "205.64",
                "cp": "207.50",
                "v": "21593"
            },
            {
                "t": "1738589805",
                "ap": "205.64",
                "cp": "207.50",
                "v": "21593"
            },
            {
                "t": "1738589913",
                "ap": "205.68",
                "cp": "207.50",
                "v": "22093"
            },
            {
                "t": "1738589997",
                "ap": "205.68",
                "cp": "207.50",
                "v": "22123"
            },
            {
                "t": "1738590057",
                "ap": "205.68",
                "cp": "207.50",
                "v": "22123"
            },
            {
                "t": "1738590137",
                "ap": "205.68",
                "cp": "207.50",
                "v": "22123"
            },
            {
                "t": "1738590202",
                "ap": "205.68",
                "cp": "207.50",
                "v": "22123"
            },
            {
                "t": "1738590300",
                "ap": "205.68",
                "cp": "207.50",
                "v": "22123"
            },
            {
                "t": "1738590418",
                "ap": "205.68",
                "cp": "207.50",
                "v": "22123"
            },
            {
                "t": "1738590780",
                "ap": "205.68",
                "cp": "207.50",
                "v": "22123"
            },
            {
                "t": "1738590885",
                "ap": "205.77",
                "cp": "208.00",
                "v": "23123"
            },
            {
                "t": "1738591157",
                "ap": "205.77",
                "cp": "208.00",
                "v": "23123"
            },
            {
                "t": "1738591201",
                "ap": "205.77",
                "cp": "208.00",
                "v": "23123"
            },
            {
                "t": "1738591374",
                "ap": "205.78",
                "cp": "208.00",
                "v": "23198"
            },
            {
                "t": "1738591580",
                "ap": "205.78",
                "cp": "208.00",
                "v": "23198"
            },
            {
                "t": "1738591684",
                "ap": "205.78",
                "cp": "208.00",
                "v": "23198"
            },
            {
                "t": "1738591907",
                "ap": "205.78",
                "cp": "208.00",
                "v": "23198"
            },
            {
                "t": "1738592729",
                "ap": "205.78",
                "cp": "208.00",
                "v": "23220"
            },
            {
                "t": "1738592788",
                "ap": "205.78",
                "cp": "208.00",
                "v": "23220"
            },
            {
                "t": "1738593303",
                "ap": "205.78",
                "cp": "208.00",
                "v": "23220"
            },
            {
                "t": "1738593515",
                "ap": "205.78",
                "cp": "208.00",
                "v": "23223"
            },
            {
                "t": "1738594805",
                "ap": "205.78",
                "cp": "208.00",
                "v": "23223"
            },
            {
                "t": "1738595708",
                "ap": "205.78",
                "cp": "208.00",
                "v": "23223"
            },
            {
                "t": "1738595863",
                "ap": "205.78",
                "cp": "208.00",
                "v": "23253"
            },
            {
                "t": "1738595969",
                "ap": "205.78",
                "cp": "208.00",
                "v": "23253"
            },
            {
                "t": "1738596042",
                "ap": "205.78",
                "cp": "208.00",
                "v": "23253"
            },
            {
                "t": "1738596106",
                "ap": "205.79",
                "cp": "206.05",
                "v": "23303"
            },
            {
                "t": "1738596124",
                "ap": "205.79",
                "cp": "206.05",
                "v": "23303"
            },
            {
                "t": "1738596184",
                "ap": "205.79",
                "cp": "206.05",
                "v": "23303"
            },
            {
                "t": "1738596266",
                "ap": "205.79",
                "cp": "206.05",
                "v": "23303"
            },
            {
                "t": "1738596426",
                "ap": "205.79",
                "cp": "208.00",
                "v": "23385"
            },
            {
                "t": "1738596580",
                "ap": "205.79",
                "cp": "208.00",
                "v": "23390"
            },
            {
                "t": "1738596603",
                "ap": "205.79",
                "cp": "208.00",
                "v": "23390"
            },
            {
                "t": "1738596676",
                "ap": "205.79",
                "cp": "208.00",
                "v": "23390"
            },
            {
                "t": "1738597249",
                "ap": "205.79",
                "cp": "208.00",
                "v": "23390"
            },
            {
                "t": "1738597290",
                "ap": "205.80",
                "cp": "207.50",
                "v": "23489"
            },
            {
                "t": "1738597341",
                "ap": "205.80",
                "cp": "207.50",
                "v": "23489"
            },
            {
                "t": "1738597416",
                "ap": "205.80",
                "cp": "207.50",
                "v": "23519"
            },
            {
                "t": "1738598402",
                "ap": "205.80",
                "cp": "207.50",
                "v": "23519"
            },
            {
                "t": "1738598494",
                "ap": "205.80",
                "cp": "207.50",
                "v": "23519"
            }
        ],
        "NSE": []
    }
}